iads/__init__.py
iads/classifiers/__init__.py
iads/classifiers/_classifiers.py
iads/clustering/__init__.py
iads/clustering/_clustering.py
iads/evaluation/__init__.py
iads/evaluation/_evaluation.py
iads/text/__init__.py
iads/text/_porter.py
iads/text/_processing.py
iads/utils/__init__.py
iads/utils/_utils.py
iads-0.1.0.dist-info/METADATA
iads-0.1.0.dist-info/WHEEL
iads-0.1.0.dist-info/top_level.txt
iads-0.1.0.dist-info/RECORD
